Metadata-Version: 2.4
Name: huscy.projects
Version: 1.12.0
Summary: Managing projects in a research context.
Project-URL: homepage, https://bitbucket.org/huscy/projects
Author-email: Anne-Cathrin Brenner <anne-cathrin-brenner@posteo.de>, Mathias Goldau <goldau@cbs.mpg.de>, Stefan Bunde <stefanbunde+git@posteo.de>
License-Expression: AGPL-3.0-or-later
License-File: LICENSE
Classifier: Development Status :: 5 - Production/Stable
Classifier: Framework :: Django
Classifier: Framework :: Django :: 4.2
Classifier: Framework :: Django :: 5.1
Classifier: Framework :: Django :: 5.2
Classifier: Operating System :: OS Independent
Classifier: Programming Language :: Python
Classifier: Programming Language :: Python :: 3
Classifier: Programming Language :: Python :: 3 :: Only
Classifier: Programming Language :: Python :: 3.9
Classifier: Programming Language :: Python :: 3.10
Classifier: Programming Language :: Python :: 3.11
Classifier: Programming Language :: Python :: 3.12
Classifier: Programming Language :: Python :: 3.13
Requires-Dist: django-guardian>=2.4
Requires-Dist: django-reversion>=4
Requires-Dist: django>=4.2
Requires-Dist: djangorestframework>=3.14
Requires-Dist: drf-nested-routers>=0.92
Provides-Extra: development
Requires-Dist: psycopg2-binary; extra == 'development'
Provides-Extra: testing
Requires-Dist: tox; extra == 'testing'
Requires-Dist: watchdog; extra == 'testing'
